zcbor/__init__.py
zcbor/include/zcbor_common.h
zcbor/include/zcbor_decode.h
zcbor/include/zcbor_encode.h
zcbor/include/zcbor_print.h
zcbor/include/zcbor_tags.h
zcbor/src/zcbor_common.c
zcbor/src/zcbor_decode.c
zcbor/src/zcbor_encode.c
zcbor/src/zcbor_print.c
zcbor/zcbor/VERSION
zcbor/zcbor/prelude.cddl
zcbor/zcbor/zcbor.py
zcbor-0.9.1.dist-info/LICENSE
zcbor-0.9.1.dist-info/METADATA
zcbor-0.9.1.dist-info/WHEEL
zcbor-0.9.1.dist-info/entry_points.txt
zcbor-0.9.1.dist-info/top_level.txt
zcbor-0.9.1.dist-info/RECORD
