Metadata-Version: 2.1
Name: zcbor
Version: 0.9.1
Summary: Code generation and data validation using CDDL schemas
Author: Nordic Semiconductor ASA
Maintainer-email: Øyvind Rønningstad <oyvind.ronningstad@nordicsemi.no>
License: Apache
Project-URL: Homepage, https://github.com/NordicSemiconductor/zcbor
Classifier: Development Status :: 4 - Beta
Classifier: Intended Audience :: Developers
Classifier: License :: OSI Approved :: Apache Software License
Classifier: Programming Language :: Python :: 3
Classifier: Programming Language :: C
Classifier: Topic :: File Formats :: JSON :: JSON Schema
Classifier: Topic :: Software Development :: Build Tools
Classifier: Topic :: Software Development :: Code Generators
Requires-Python: >=3.8
License-File: LICENSE
Requires-Dist: cbor2>=5.4.2.post1
Requires-Dist: pyyaml>=5.4.1
Requires-Dist: regex>=2022.3.15
